outlier/__init__.py
outlier/outlier.py
outlier_python_souravdlboy-1.1.dist-info/LICENSE
outlier_python_souravdlboy-1.1.dist-info/METADATA
outlier_python_souravdlboy-1.1.dist-info/WHEEL
outlier_python_souravdlboy-1.1.dist-info/top_level.txt
outlier_python_souravdlboy-1.1.dist-info/RECORD
