Metadata-Version: 2.1
Name: outlier-python-souravdlboy
Version: 1.1
Summary: Python package for Outlier Removal Algorithm using z_score or iqr.
Home-page: https://github.com/souravs17031999/outlier-python
Author: sourav kumar
Author-email: sauravkumarsct@gmail.com
License: UNKNOWN
Platform: UNKNOWN
Classifier: Programming Language :: Python :: 3
Classifier: Programming Language :: Python :: 3.2
Classifier: Programming Language :: Python :: 3.3
Classifier: Programming Language :: Python :: 3.4
Classifier: Programming Language :: Python :: 3.5
Classifier: Programming Language :: Python :: 3.6
Classifier: Programming Language :: Python :: 3.7
Classifier: License :: OSI Approved :: MIT License
Classifier: Operating System :: OS Independent
Requires-Python: >=3.0
